supycache/__init__.py
supycache/cdf.py
supycache/backends/__init__.py
supycache/backends/base.py
supycache/backends/dict_cache.py
supycache/backends/memcached.py
supycache-0.3.0.dist-info/DESCRIPTION.rst
supycache-0.3.0.dist-info/METADATA
supycache-0.3.0.dist-info/RECORD
supycache-0.3.0.dist-info/WHEEL
supycache-0.3.0.dist-info/metadata.json
supycache-0.3.0.dist-info/top_level.txt
