Metadata-Version: 2.0
Name: supycache
Version: 0.3.0
Summary: Simple yet capable caching decorator for python
Home-page: https://github.com/lonetwin/supycache
Author: Steven Fernandez
Author-email: steve@lonetwin.net
License: MIT
Keywords: cache,caching,memcached,redis,memoize,memoization
Platform: UNKNOWN
Classifier: Development Status :: 4 - Beta
Classifier: Intended Audience :: Developers
Classifier: Topic :: Software Development :: Libraries
Classifier: License :: OSI Approved :: MIT License
Classifier: Programming Language :: Python :: 2.7
Classifier: Programming Language :: Python :: 3
Classifier: Programming Language :: Python :: 3.2
Classifier: Programming Language :: Python :: 3.3
Classifier: Programming Language :: Python :: 3.4
